{"Hot Chocolate Fudge": 372000, "Pista Double Scoop": 14940, "Death by Chocolate": 305280, "Cake Fudge": 361200, "Vanilla Single Scoop": 84100, "Dry Fruit Double Scoop": 16650, "Vanilla Double Scoop": 176320, "Chocolate Europa Double Scoop": 17700, "Fig and Honey Single Scoop": 8940, "Butterscotch Single Scoop": 100560, "Cafe Caramel": 122880, "Caramel Crunch Double Scoop": 16700, "Butterscotch Double Scoop": 12870, "Fig and Honey Double Scoop": 14310, "Mint Fudge": 10200, "Dry Fruit Single Scoop": 11460, "Banana Split": 10360, "Trilogy": 13600, "Chocolate Europa Single Scoop": 12180, "Pista Single Scoop": 9180, "Dew Drop Sundae": 13200, "Rocky Road Single Scoop": 7500, "Caramel Crunch Single Scoop": 12250, "Almond Fudge": 10650, "Rocky Road Double Scoop": 4560}